pytest_snapshot/__init__.py
pytest_snapshot/_utils.py
pytest_snapshot/_version.py
pytest_snapshot/plugin.py
pytest_snapshot-0.9.0.dist-info/LICENSE
pytest_snapshot-0.9.0.dist-info/METADATA
pytest_snapshot-0.9.0.dist-info/WHEEL
pytest_snapshot-0.9.0.dist-info/entry_points.txt
pytest_snapshot-0.9.0.dist-info/top_level.txt
pytest_snapshot-0.9.0.dist-info/RECORD
